ipython_IDV/__init__.py
ipython_IDV/drilsdown.py
ipython_IDV-2.4.7.dist-info/DESCRIPTION.rst
ipython_IDV-2.4.7.dist-info/METADATA
ipython_IDV-2.4.7.dist-info/RECORD
ipython_IDV-2.4.7.dist-info/WHEEL
ipython_IDV-2.4.7.dist-info/metadata.json
ipython_IDV-2.4.7.dist-info/top_level.txt
tests/__init__.py
tests/test_sample.py
