Metadata-Version: 2.0
Name: ipython-IDV
Version: 2.4.7
Summary: This project allows users to use Unidata's IDV with jupyter notebooks 
Home-page: UNKNOWN
Author: Drilsdown team
Author-email: drilsdown@unidata.ucar.edu
License: UNKNOWN
Platform: UNKNOWN
Classifier: Development Status :: 2 - Pre-Alpha
Classifier: Programming Language :: Python
Classifier: Programming Language :: Python :: 2
Classifier: Programming Language :: Python :: 2.7
Classifier: Programming Language :: Python :: 3
Classifier: Programming Language :: Python :: 3.4
Classifier: Programming Language :: Python :: 3.5
Classifier: Programming Language :: Python :: 3.6
Requires-Dist: ipython
